numpy_audio_limiter-0.1.0.dist-info/METADATA
numpy_audio_limiter-0.1.0.dist-info/WHEEL
numpy_audio_limiter/__init__.py
numpy_audio_limiter/numpy_audio_limiter.abi3.so
numpy_audio_limiter-0.1.0.dist-info/RECORD
