Metadata-Version: 2.4
Name: numpy-audio-limiter
Version: 0.1.0
Summary: Simple Python audio limiter implemented in Rust (pyo3, operates on numpy array).
Author: Iver Jordal
License: MIT
Requires-Python: >=3.9
